{
  "name" : "Face Off",
  "unique_name": "faceoff",
  "instructions" : "",
  "recipe_names" : ["emo_face"],
  "persist_as_results" : ["emo_intelligence"],
  "stages" :
    [
      {
        "friendly_name": "What's Your Mood?",
        "view_name": "Survey",
        "client_view_name": "EmotionsSurvey",
        "data": [
          {
            "question_id": "emotion11",
            "topic": "emotion",
            "question_type": "select_by_icon",
            "question": "How do you feel right now?",
            "options": [
                {
                    "label": "happy",
                    "value": "happy"
                },
                {
                    "value": "bored",
                    "label": "bored"
                },
                {
                    "value": "angry",
                    "label": "angry"
                },
                {
                    "value": "sad",
                    "label": "sad"
                },
                {
                    "value": "amused",
                    "label": "amused"
                },
                {
                    "label": "surprised",
                    "value": "surprised"
                },
                {
                    "label": "proud",
                    "value": "proud"
                },
                {
                    "label": "embarrassed",
                    "value": "embarrassed"
                },
                {
                    "value": "disgusted",
                    "label": "disgusted"
                },
                {
                    "value": "afraid",
                    "label": "afraid"
                },
                {
                    "value": "ashamed",
                    "label": "ashamed"
                }
            ]
          }
        ]
      },      
      {
        "friendly_name": "Face Off",
        "instructions": "Find the emotion behind the face.",
        "view_name": "FaceOff",
        "client_view_name": "FaceOff",
        "image_url_base": "",
        "stage_type": "primary_only",
        "time_to_show": 99999,
        "primary_multiplier": 2,
        "secondary_multiplier": 1,
        "difficulty_multiplier": 1, 
        "number_of_images": 3,
        "number_of_choices": 4
      },
      {
        "friendly_name": "Face Off",
        "instructions": "Find the emotion behind the face.",
        "view_name": "FaceOff",
        "client_view_name": "FaceOff",
        "image_url_base": "",
        "stage_type": "primary_only",
        "time_to_show": 1000,
        "primary_multiplier": 2,
        "secondary_multiplier": 1,
        "difficulty_multiplier": 1,
        "number_of_images": 3, 
        "number_of_choices": 4
      },
      {
        "friendly_name": "Face Off",
        "instructions": "Find the emotion behind the face.",
        "view_name": "FaceOff",
        "client_view_name": "FaceOff",
        "image_url_base": "",
        "stage_type": "primary_secondary",
        "time_to_show": 1000,
        "primary_multiplier": 2,
        "secondary_multiplier": 1,
        "difficulty_multiplier": 2,
        "number_of_images": 3, 
        "number_of_choices": 4
      },      
      {
        "friendly_name": "Face Off",
        "instructions": "Find the emotion behind the face.",
        "view_name": "FaceOff",
        "client_view_name": "FaceOff",
        "image_url_base": "",
        "stage_type": "primary_nuanced",
        "time_to_show": 500,
        "primary_multiplier": 2,
        "secondary_multiplier": 1,
        "difficulty_multiplier": 3,
        "number_of_images": 3, 
        "number_of_choices": 4
      }      
    ]
}